nbterm/__init__.py
nbterm/_version.py
nbterm/cell.py
nbterm/format.py
nbterm/help.py
nbterm/key_bindings.py
nbterm/nbterm.py
nbterm/notebook.py
nbterm-0.0.13.dist-info/LICENSE
nbterm-0.0.13.dist-info/METADATA
nbterm-0.0.13.dist-info/WHEEL
nbterm-0.0.13.dist-info/entry_points.txt
nbterm-0.0.13.dist-info/top_level.txt
nbterm-0.0.13.dist-info/RECORD
