Metadata-Version: 2.1
Name: nbterm
Version: 0.0.13
Summary: A tool for viewing, editing and executing Jupyter Notebooks in the terminal
Home-page: https://github.com/davidbrochart/nbterm.git
Author: David Brochart
Author-email: david.brochart@gmail.com
Classifier: Programming Language :: Python :: 3
Classifier: License :: OSI Approved :: MIT License
Classifier: Operating System :: OS Independent
Requires-Python: >=3.7
Provides-Extra: test
License-File: LICENSE
